jdbc_wrapper/__init__.py
jdbc_wrapper/abc.py
jdbc_wrapper/connection.py
jdbc_wrapper/connection_async.py
jdbc_wrapper/const.py
jdbc_wrapper/cursor.py
jdbc_wrapper/cursor_async.py
jdbc_wrapper/exceptions.py
jdbc_wrapper/log.py
jdbc_wrapper/log.toml
jdbc_wrapper/pipeline.py
jdbc_wrapper/types.py
jdbc_wrapper/utils.py
jdbc_wrapper/utils_async.py
jdbc_wrapper/_loader/__init__.py
jdbc_wrapper/_loader/base.py
jdbc_wrapper/_loader/github.py
jdbc_wrapper/_loader/mssql.py
jdbc_wrapper/_loader/postgresql.py
jdbc_wrapper/_loader/sqlite.py
jdbc_wrapper/_sqlalchemy/__init__.py
jdbc_wrapper/_sqlalchemy/connector.py
jdbc_wrapper/_sqlalchemy/mssql.py
jdbc_wrapper/_sqlalchemy/postgresql.py
jdbc_wrapper/_sqlalchemy/sqlite.py
jdbc_wrapper/_sqlalchemy/_connector/__init__.py
jdbc_wrapper/_sqlalchemy/_connector/config.py
jdbc_wrapper/_sqlalchemy/_connector/connection_async.py
jdbc_wrapper/_sqlalchemy/_connector/cursor_async.py
jdbc_wrapper/_sqlalchemy/_connector/main.py
jdbc_wrapper/_sqlalchemy/_connector/utils_async.py
jdbc_wrapper-0.1.0.dist-info/METADATA
jdbc_wrapper-0.1.0.dist-info/WHEEL
jdbc_wrapper-0.1.0.dist-info/licenses/LICENSE
jdbc_wrapper-0.1.0.dist-info/RECORD
