Metadata-Version: 2.3
Name: jdbc-wrapper
Version: 0.1.0
Summary: Add your description here
Author-email: phi <phi.friday@gmail.com>
License: MIT License
License-File: LICENSE
Classifier: Development Status :: 2 - Pre-Alpha
Classifier: Framework :: AsyncIO
Classifier: Programming Language :: Python :: 3
Classifier: Programming Language :: Python :: 3.9
Classifier: Programming Language :: Python :: 3.10
Classifier: Programming Language :: Python :: 3.11
Classifier: Programming Language :: Python :: 3.12
Classifier: Programming Language :: Python :: Implementation :: CPython
Requires-Python: >=3.9
Requires-Dist: jpype1>=1.2.1
Requires-Dist: tomli>=1.1.0; python_version < '3.11'
Requires-Dist: typing-extensions>=4.4.0
Provides-Extra: asyncio
Requires-Dist: greenlet; extra == 'asyncio'
Provides-Extra: sqlalchemy
Requires-Dist: greenlet; extra == 'sqlalchemy'
Requires-Dist: sqlalchemy[asyncio]>=2; extra == 'sqlalchemy'
Provides-Extra: test
Requires-Dist: anyio>=4.4.0; extra == 'test'
Requires-Dist: filelock>=3.15.4; extra == 'test'
Requires-Dist: greenlet; extra == 'test'
Requires-Dist: pytest-cov>=5.0.0; extra == 'test'
Requires-Dist: pytest-dotenv>=0.5.2; extra == 'test'
Requires-Dist: pytest-icdiff>=0.9; extra == 'test'
Requires-Dist: pytest-xdist[psutil]>=3.6.1; extra == 'test'
Requires-Dist: pytest>=8.2.2; extra == 'test'
Requires-Dist: sqlalchemy[asyncio]>=2; extra == 'test'
Provides-Extra: typing
Requires-Dist: types-greenlet; extra == 'typing'
